connectwise/__init__.py
connectwise/__version__.py
connectwise/client.py
connectwise/exceptions.py
connectwise/company/__init__.py
connectwise/company/companies/__init__.py
connectwise/company/companies/count.py
connectwise/company/companies/get.py
connectwise/company/configurations/__init__.py
connectwise/company/configurations/get.py
connectwise/company/configurations/patch.py
connectwise/company/contacts/__init__.py
connectwise/company/contacts/get.py
connectwise/service/__init__.py
connectwise/service/boards/__init__.py
connectwise/service/boards/get.py
connectwise/service/boardstatuses/__init__.py
connectwise/service/boardstatuses/get.py
connectwise/service/notes/__init__.py
connectwise/service/notes/create.py
connectwise/service/notes/get.py
connectwise/service/notes/get_all.py
connectwise/service/notes/update.py
connectwise/service/priorities/__init__.py
connectwise/service/priorities/get.py
connectwise/service/tickets/__init__.py
connectwise/service/tickets/create.py
connectwise/service/tickets/get.py
connectwise/service/tickets/update.py
connectwise/time/__init__.py
connectwise/time/entries/__init__.py
connectwise/time/entries/get.py
test/__init__.py
test/test_client.py
test/test_company.py
pyRESTcw-0.0.15.dist-info/AUTHORS
pyRESTcw-0.0.15.dist-info/LICENSE.txt
pyRESTcw-0.0.15.dist-info/METADATA
pyRESTcw-0.0.15.dist-info/WHEEL
pyRESTcw-0.0.15.dist-info/top_level.txt
pyRESTcw-0.0.15.dist-info/RECORD
