Metadata-Version: 2.1
Name: pyRESTcw
Version: 0.0.15
Summary: Python client library for Connectwise REST API
Home-page: https://github.com/Aidenwebb/connectwise-rest-api-python
Author: Aidenwebb
Author-email: unknown@unknown.com
License: Apache 2.0
Keywords: connectwise,pyRESTcw,python connectwise
Platform: Posix; MacOS X; Windows
Classifier: Development Status :: 3 - Alpha
Classifier: Intended Audience :: Developers
Classifier: License :: OSI Approved :: Apache Software License
Classifier: Operating System :: OS Independent
Classifier: Programming Language :: Python :: 2.7
Classifier: Programming Language :: Python :: 3.2
Classifier: Programming Language :: Python :: 3.4
Classifier: Programming Language :: Python :: 3.6
Classifier: Topic :: Internet
